Faker_mail/__init__.py
Faker_mail/email.py
Faker_mail/message.py
FakerMail-1.0.dist-info/LICENSE
FakerMail-1.0.dist-info/METADATA
FakerMail-1.0.dist-info/WHEEL
FakerMail-1.0.dist-info/top_level.txt
FakerMail-1.0.dist-info/RECORD
